applocker/__init__.py
applocker/conditions.py
applocker/policy.py
applocker/rules.py
applocker/utils.py
applocker-1.1.2.dist-info/licenses/LICENSE
applocker-1.1.2.dist-info/METADATA
applocker-1.1.2.dist-info/WHEEL
applocker-1.1.2.dist-info/top_level.txt
applocker-1.1.2.dist-info/RECORD
