Metadata-Version: 2.4
Name: applocker
Version: 1.1.2
Summary: AppLocker Policy parser and emitter for Python
Requires-Python: >=3.9
License-File: LICENSE
Dynamic: license-file
